xpathreader/__init__.py
xpathreader/xpathreader.py
xpathreader-1.1.3.dist-info/LICENSE
xpathreader-1.1.3.dist-info/METADATA
xpathreader-1.1.3.dist-info/WHEEL
xpathreader-1.1.3.dist-info/top_level.txt
xpathreader-1.1.3.dist-info/RECORD
