Metadata-Version: 2.1
Name: xpathreader
Version: 1.1.3
Summary: Reads xPath files. Documentation: https://regmi-solutions.de/xpathreader
Home-page: https://regmi-solutions.de/xpathreader
Author: Bijay Regmi
Author-email: bijay.regmi@uni-bonn.de
License: MIT
Platform: UNKNOWN
Classifier: Programming Language :: Python :: 3
Classifier: License :: OSI Approved :: MIT License
Classifier: Operating System :: OS Independent
Requires-Python: >=3.6
